README.rst
setup.py
gattools/__init__.py
gattools/gattools.py
gattools.egg-info/PKG-INFO
gattools.egg-info/SOURCES.txt
gattools.egg-info/dependency_links.txt
gattools.egg-info/top_level.txt