Metadata-Version: 1.1
Name: gattools
Version: 0.0.1
Summary: Tools for creating and processing Genome Annotation Table (GAT) files
Home-page: https://github.com/genestation/gattools
Author: Mara Kim
Author-email: mara@autochthe.net
License: UNKNOWN
Keywords: gat
Platform: UNKNOWN
Classifier: Development Status :: 1 - Planning
Classifier: Intended Audience :: Science/Research
Classifier: Topic :: Scientific/Engineering :: Bio-Informatics
Classifier: License :: OSI Approved :: GNU General Public License v3 (GPLv3)
Classifier: Programming Language :: Python :: 3
Classifier: Programming Language :: Python :: 3.4
Classifier: Programming Language :: Python :: 3.5
Classifier: Programming Language :: Python :: 3.6
